lixinger_openapi/__init__.py
lixinger_openapi/query.py
lixinger_openapi/token.py
lixinger_openapi-1.0.2.dist-info/DESCRIPTION.rst
lixinger_openapi-1.0.2.dist-info/METADATA
lixinger_openapi-1.0.2.dist-info/RECORD
lixinger_openapi-1.0.2.dist-info/WHEEL
lixinger_openapi-1.0.2.dist-info/metadata.json
lixinger_openapi-1.0.2.dist-info/top_level.txt
