Metadata-Version: 2.0
Name: lixinger-openapi
Version: 1.0.2
Summary: lixinger openapi
Home-page: https://github.com/ShekiLyu/lixinger-openapi
Author: sheki lyu
Author-email: lvxueji@gmail.com
License: Apache License v2
Platform: UNKNOWN
Classifier: Operating System :: OS Independent
Classifier: Programming Language :: Python :: 2.7
Classifier: Programming Language :: Python :: 3
Requires-Dist: pandas
Requires-Dist: requests
